{"errors":[],"warnings":[],"namedChunkGroups":{"app":{"chunks":[7,0,3],"assets":["webpack-runtime-1c094a846dc3f56d1f39.js","webpack-runtime-1c094a846dc3f56d1f39.js.map","styles.74cae2c7dbe7d6267429.css","styles-27b1e23b7014bbfaee58.js","styles-27b1e23b7014bbfaee58.js.map","app-0129325ef809a871099b.js","app-0129325ef809a871099b.js.map"],"children":{},"childAssets":{}},"component---src-pages-404-js":{"chunks":[1,4],"assets":["1-1530da1c26a1f6fbed3c.js","1-1530da1c26a1f6fbed3c.js.map","component---src-pages-404-js-ac75d44bc49b7854f682.js","component---src-pages-404-js-ac75d44bc49b7854f682.js.map"],"children":{},"childAssets":{}},"component---src-pages-index-js":{"chunks":[0,1,2,5],"assets":["styles.74cae2c7dbe7d6267429.css","styles-27b1e23b7014bbfaee58.js","styles-27b1e23b7014bbfaee58.js.map","1-1530da1c26a1f6fbed3c.js","1-1530da1c26a1f6fbed3c.js.map","2-4b549ab8c06ed8616733.js","2-4b549ab8c06ed8616733.js.map","component---src-pages-index-js-638137d09279ab1044b0.js","component---src-pages-index-js-638137d09279ab1044b0.js.map"],"children":{},"childAssets":{}},"component---src-pages-mobile-js":{"chunks":[0,1,2,6],"assets":["styles.74cae2c7dbe7d6267429.css","styles-27b1e23b7014bbfaee58.js","styles-27b1e23b7014bbfaee58.js.map","1-1530da1c26a1f6fbed3c.js","1-1530da1c26a1f6fbed3c.js.map","2-4b549ab8c06ed8616733.js","2-4b549ab8c06ed8616733.js.map","component---src-pages-mobile-js-01f80e9366d99cf41cf6.js","component---src-pages-mobile-js-01f80e9366d99cf41cf6.js.map"],"children":{},"childAssets":{}}},"assetsByChunkName":{"app":["webpack-runtime-1c094a846dc3f56d1f39.js","styles.74cae2c7dbe7d6267429.css","styles-27b1e23b7014bbfaee58.js","app-0129325ef809a871099b.js"],"component---src-pages-404-js":["1-1530da1c26a1f6fbed3c.js","component---src-pages-404-js-ac75d44bc49b7854f682.js"],"component---src-pages-index-js":["styles.74cae2c7dbe7d6267429.css","styles-27b1e23b7014bbfaee58.js","1-1530da1c26a1f6fbed3c.js","2-4b549ab8c06ed8616733.js","component---src-pages-index-js-638137d09279ab1044b0.js"],"component---src-pages-mobile-js":["styles.74cae2c7dbe7d6267429.css","styles-27b1e23b7014bbfaee58.js","1-1530da1c26a1f6fbed3c.js","2-4b549ab8c06ed8616733.js","component---src-pages-mobile-js-01f80e9366d99cf41cf6.js"]}}